README.md
setup.cfg
setup.py
voximplant_client/__init__.py
voximplant_client/cli.py
voximplant_client/client.py
voximplant_client/exceptions.py
voximplant_client/helpers.py
voximplant_client/http_client.py
voximplant_client/result.py
voximplant_client.egg-info/PKG-INFO
voximplant_client.egg-info/SOURCES.txt
voximplant_client.egg-info/dependency_links.txt
voximplant_client.egg-info/entry_points.txt
voximplant_client.egg-info/not-zip-safe
voximplant_client.egg-info/requires.txt
voximplant_client.egg-info/top_level.txt
voximplant_client/entities/__init__.py
voximplant_client/entities/applications.py
voximplant_client/entities/base.py
voximplant_client/entities/history.py
voximplant_client/entities/qeueus.py
voximplant_client/entities/rules.py
voximplant_client/entities/scenarios.py
voximplant_client/entities/users.py