Metadata-Version: 1.0
Name: voximplant-client
Version: 0.0.5
Summary: Voximplant.com API client.
Home-page: https://github.com/gdml/voximplant-client/
Author: Fedor Borshev
Author-email: f@f213.in
License: MIT
Platform: UNKNOWN
